UEManifestReader/__init__.py
UEManifestReader/converter.py
UEManifestReader/enums.py
UEManifestReader/classes/FChunkDataList.py
UEManifestReader/classes/FCustomFields.py
UEManifestReader/classes/FFileManifestList.py
UEManifestReader/classes/FManifestData.py
UEManifestReader/classes/FManifestHeader.py
UEManifestReader/classes/FManifestMeta.py
UEManifestReader/classes/__init__.py
UEManifestReader/classes/stream_reader.py
UEManifestReader-0.0.1.dist-info/METADATA
UEManifestReader-0.0.1.dist-info/WHEEL
UEManifestReader-0.0.1.dist-info/top_level.txt
UEManifestReader-0.0.1.dist-info/RECORD
