Metadata-Version: 2.1
Name: UEManifestReader
Version: 0.0.1
Summary: Read and parse Unreal Engine Manifests
Home-page: https://github.com/LupusLeaks/UEManifestReader
Author: UNKNOWN
Author-email: admin@ezfn.dev
License: MIT
Platform: UNKNOWN
Requires-Dist: aiohttp
Requires-Dist: bitstring
